pdfire/__init__.py
pdfire/bytes_result.py
pdfire/client.py
pdfire/conversion.py
pdfire/conversion_params.py
pdfire/errors.py
pdfire/example.py
pdfire/merge_params.py
pdfire/result.py
pdfire-2.0.0.dist-info/LICENSE
pdfire-2.0.0.dist-info/METADATA
pdfire-2.0.0.dist-info/WHEEL
pdfire-2.0.0.dist-info/top_level.txt
pdfire-2.0.0.dist-info/RECORD
