Metadata-Version: 2.1
Name: pdfire
Version: 2.0.0
Summary: Python client for the PDFire.io API.
Home-page: https://github.com/modernice/pdfire-python
Author: modernice Ltd.
Author-email: info@modernice.ltd
License: MIT
Keywords: PDFire,client,API,library,PDF,converter
Platform: UNKNOWN
Classifier: Development Status :: 5 - Production/Stable
Classifier: Intended Audience :: Developers
Classifier: Operating System :: OS Independent
Classifier: Topic :: Software Development :: Libraries :: Python Modules
Classifier: License :: OSI Approved :: MIT License
Requires-Python: >=3.5
Requires-Dist: python-dateutil
